3LFCC/src/adc.v
`default_nettype none

module adc #(
    parameter address = 7'd0
) (
    input clk,

    input [1:0] channel,

    output reg [15:0] outputData = 0,

    output reg dataReady = 1,
    input enable,

    output reg [1:0] instructionI2C = 0,
    output reg enableI2C = 0,

    output reg [7:0] byteToSendI2C = 0,
    input [7:0] byteReceivedI2C,

    input completeI2C
);

    // setup config
    reg [15:0] setupRegister = {
        1'b1, // Start Conversion
        3'b100, // Channel 0 Single ended
        3'b001, // FSR +- 4.096v
        1'b1, // Single shot mode
        3'b111, // 128 SPS
        1'b0, // Traditional Comparator
        1'b0, // Active low alert
        1'b0, // Non latching
        2'b11 // Disable comparator
    };

    localparam CONFIG_REGISTER = 8'b00000001;
    localparam CONVERSION_REGISTER = 8'b00000000;

    localparam TASK_SETUP = 0;
    localparam TASK_CHECK_DONE = 1;
    localparam TASK_CHANGE_REG = 2;
    localparam TASK_READ_VALUE = 3;

    localparam INST_START_TX = 0;
    localparam INST_STOP_TX = 1;
    localparam INST_READ_BYTE = 2;
    localparam INST_WRITE_BYTE = 3;

    localparam STATE_IDLE = 0;
    localparam STATE_RUN_TASK = 1;
    localparam STATE_WAIT_FOR_I2C = 2;
    localparam STATE_INC_SUB_TASK = 3;
    localparam STATE_DONE = 4;
    localparam STATE_DELAY = 5;

    reg [1:0] taskIndex = 0;
    reg [2:0] subTaskIndex = 0;

    reg [4:0] state = STATE_IDLE;

    reg [7:0] counter = 0;

    reg processStarted = 0;

    always @(posedge clk) begin
        case (state)
            STATE_IDLE: begin
                if (enable) begin
                    state <= STATE_RUN_TASK;
                    taskIndex <= 0;
                    subTaskIndex <= 0;
                    dataReady <= 0;
                    counter <= 0;
                end
            end
            STATE_RUN_TASK: begin
                case ({taskIndex,subTaskIndex})
                    {TASK_SETUP,3'd0},
                    {TASK_CHECK_DONE,3'd1},
                    {TASK_CHANGE_REG,3'd1},
                    {TASK_READ_VALUE,3'd0}: begin
                        instructionI2C <= INST_START_TX;
                        enableI2C <= 1;
                        state <= STATE_WAIT_FOR_I2C;
                    end
                    {TASK_SETUP,3'd1},
                    {TASK_CHANGE_REG,3'd2},
                    {TASK_CHECK_DONE,3'd2},
                    {TASK_READ_VALUE,3'd1}: begin
                        instructionI2C <= INST_WRITE_BYTE;
                        byteToSendI2C <= {
                            address,
                            (taskIndex == TASK_CHECK_DONE || taskIndex == TASK_READ_VALUE)
                             ? 1'b1 : 1'b0
                        };
                        enableI2C <= 1;
                        state <= STATE_WAIT_FOR_I2C;
                    end
                    {TASK_SETUP,3'd5},
                    {TASK_CHECK_DONE,3'd5},
                    {TASK_CHANGE_REG,3'd4},
                    {TASK_READ_VALUE,3'd5}: begin
                        instructionI2C <= INST_STOP_TX;
                        enableI2C <= 1;
                        state <= STATE_WAIT_FOR_I2C;
                    end
                    {TASK_SETUP,3'd2},
                    {TASK_CHANGE_REG,3'd3}: begin
                        instructionI2C <= INST_WRITE_BYTE;
                        byteToSendI2C <= taskIndex == TASK_SETUP ?
                            CONFIG_REGISTER : CONVERSION_REGISTER;
                        enableI2C <= 1;
                        state <= STATE_WAIT_FOR_I2C;
                    end
                    {TASK_SETUP,3'd3}: begin
                        instructionI2C <= INST_WRITE_BYTE;
                        byteToSendI2C <= {
                            setupRegister[15] ? 1'b1 : 1'b0,
                            3'b001,
                            setupRegister[11:8]
                        };
                        enableI2C <= 1;
                        state <= STATE_WAIT_FOR_I2C;
                    end
                    {TASK_SETUP,3'd4}: begin
                        instructionI2C <= INST_WRITE_BYTE;
                        byteToSendI2C <= setupRegister[7:0];
                        enableI2C <= 1;
                        state <= STATE_WAIT_FOR_I2C;
                    end
                    {TASK_CHECK_DONE,3'd0}: begin
                        state <= STATE_DELAY;
                    end
                    {TASK_CHECK_DONE,3'd3},
                    {TASK_READ_VALUE,3'd2}: begin
                        instructionI2C <= INST_READ_BYTE;
                        enableI2C <= 1;
                        state <= STATE_WAIT_FOR_I2C;
                    end
                    {TASK_CHECK_DONE,3'd4},
                    {TASK_READ_VALUE,3'd3}: begin
                        instructionI2C <= INST_READ_BYTE;
                        outputData[15:8] <= byteReceivedI2C;
                        enableI2C <= 1;
                        state <= STATE_WAIT_FOR_I2C;
                    end
                    {TASK_CHANGE_REG,3'd0}: begin
                        if (outputData[15])
                            state <= STATE_INC_SUB_TASK;
                        else begin
                            subTaskIndex <= 0;
                            taskIndex <= TASK_CHECK_DONE;
                        end
                    end
                    {TASK_READ_VALUE,3'd4}: begin
                        state <= STATE_INC_SUB_TASK;
                        outputData[7:0] <= byteReceivedI2C;
                    end
                    default:
                        state <= STATE_INC_SUB_TASK;
                endcase
            end
            STATE_WAIT_FOR_I2C: begin
                if (~processStarted && ~completeI2C)
                    processStarted <= 1;
                else if (completeI2C && processStarted) begin
                    state <= STATE_INC_SUB_TASK;
                    processStarted <= 0;
                    enableI2C <= 0;
                end
            end
            STATE_INC_SUB_TASK: begin
                state <= STATE_RUN_TASK;
                if (subTaskIndex == 3'd5) begin
                    subTaskIndex <= 0;
                    if (taskIndex == TASK_READ_VALUE) begin
                        state <= STATE_DONE;
                    end
                    else
                        taskIndex <= taskIndex + 1;
                    end
                else
                    subTaskIndex <= subTaskIndex + 1;
            end
            STATE_DELAY: begin
                counter <= counter + 1;
                if (counter == 8'b11111111) begin
                    state <= STATE_INC_SUB_TASK;
                end
            end
            STATE_DONE: begin
                dataReady <= 1;
                if (~enable)
                    state <= STATE_IDLE;
            end
            default: begin
                state <= STATE_IDLE;
            end
        endcase
    end

endmodule

3LFCC/src/i2c.v
`default_nettype none

module i2c (
    input clk,

    input sdaIn,
    output reg sdaOutReg = 1,
    output reg isSending = 0,

    output reg scl = 1,

    input [1:0] instruction, // 00 = start, 01 = stop, 10 = read + ACK, 11 = write + ACK

    input enable,

    input [7:0] byteToSend,
    output reg [7:0] byteReceived = 0,

    output reg complete
);
    
    localparam INST_START_TX = 0;
    localparam INST_STOP_TX = 1;
    localparam INST_READ_BYTE = 2;
    localparam INST_WRITE_BYTE = 3;
    localparam STATE_IDLE = 4;
    localparam STATE_DONE = 5;
    localparam STATE_SEND_ACK = 6;
    localparam STATE_RCV_ACK = 7;

    reg [6:0] clockDivider = 0;

    reg [2:0] state = STATE_IDLE;
    reg [2:0] bitToSend = 0;

    always @(posedge clk) begin
        case (state)
            STATE_IDLE: begin
                if (enable) begin
                    complete <= 0;
                    clockDivider <= 0;
                    bitToSend <= 0;
                    state <= {1'b0,instruction};
                end
            end
            INST_START_TX: begin
                isSending <= 1;
                clockDivider <= clockDivider + 1;
                if (clockDivider[6:5] == 2'b00) begin
                    scl <= 1;
                    sdaOutReg <= 1;
                end else if (clockDivider[6:5] == 2'b01) begin
                    sdaOutReg <= 0;
                end else if (clockDivider[6:5] == 2'b10) begin
                    scl <= 0;
                end else if (clockDivider[6:5] == 2'b11) begin
                    state <= STATE_DONE;
                end
            end
            INST_STOP_TX: begin
                isSending <= 1;
                clockDivider <= clockDivider + 1;
                if (clockDivider[6:5] == 2'b00) begin // Clock low period
                    scl <= 0;
                    sdaOutReg <= 0;
                end else if (clockDivider[6:5] == 2'b01) begin // Clock rising edge
                    scl <= 1;
                end else if (clockDivider[6:5] == 2'b10) begin // Clock high period
                    sdaOutReg <= 1;
                end else if (clockDivider[6:5] == 2'b11) begin // Clock falling edge
                    state <= STATE_DONE;
                end
            end
            INST_READ_BYTE: begin
                isSending <= 0;
                clockDivider <= clockDivider + 1;
                if (clockDivider[6:5] == 2'b00) begin // Clock low period
                    scl <= 0;

                end else if (clockDivider[6:5] == 2'b01) begin // Clock rising edge
                    scl <= 1;

                end else if (clockDivider == 7'b1000000) begin // Mid clock high period
                    byteReceived <= {byteReceived[6:0], sdaIn ? 1'b1 : 1'b0};

                end else if (clockDivider == 7'b1111111) begin // Mid clock low period
                    bitToSend <= bitToSend + 1;
                    if (bitToSend == 3'b111) begin
                        state <= STATE_SEND_ACK;
                    end

                end else if (clockDivider[6:5] == 2'b11) begin // Clock falling edge
                    scl <= 0;
                end
            end
            STATE_SEND_ACK: begin
                isSending <= 1;
                sdaOutReg <= 0;
                clockDivider <= clockDivider + 1;
                if (clockDivider[6:5] == 2'b01) begin
                    scl <= 1;
                end else if (clockDivider == 7'b1111111) begin
                    state <= STATE_DONE;
                end else if (clockDivider[6:5] == 2'b11) begin
                    scl <= 0;
                end
            end
            INST_WRITE_BYTE: begin
                isSending <= 1;
                clockDivider <= clockDivider + 1;
                sdaOutReg <= byteToSend[3'd7-bitToSend] ? 1'b1 : 1'b0;

                if (clockDivider[6:5] == 2'b00) begin
                    scl <= 0;
                end else if (clockDivider[6:5] == 2'b01) begin
                    scl <= 1;
                end else if (clockDivider == 7'b1111111) begin
                    bitToSend <= bitToSend + 1;
                    if (bitToSend == 3'b111) begin
                        state <= STATE_RCV_ACK;
                    end
                end else if (clockDivider[6:5] == 2'b11) begin
                    scl <= 0;
                end
            end
            STATE_RCV_ACK: begin
                isSending <= 0;
                clockDivider <= clockDivider + 1;

                if (clockDivider[6:5] == 2'b01) begin
                    scl <= 1;
                end else if (clockDivider == 7'b1111111) begin
                    state <= STATE_DONE;
                end else if (clockDivider[6:5] == 2'b11) begin
                    scl <= 0;
                end
                // else if (clockDivider == 7'b1000000) begin
                //     sdaIn should be 0
                // end
            end
            STATE_DONE: begin
                complete <= 1;
                if (~enable)
                    state <= STATE_IDLE;
            end
            default: state <= STATE_IDLE;
        endcase
    end

endmodule

examples/adc/test/adc_tb.v
module test();

    reg clk = 0;

    always
        #1  clk = ~clk;
        
    initial begin
        #100000 $finish;
    end
        

    initial begin
        $dumpfile("adc.vcd");
        $dumpvars(0,test);
    end

    wire [1:0] i2cInstruction;
    wire [7:0] i2cByteToSend;
    wire [7:0] i2cByteReceived;
    wire i2cComplete;
    wire i2cEnable;

    wire i2cSda;

    wire i2cScl;
    wire sdaIn;
    wire sdaOut;
    wire isSending;
    assign i2cSda = (isSending & ~sdaOut) ? 1'b0 : 1'b1;
    assign sdaIn = i2cSda ? 1'b1 : 1'b0;

    i2c c(
        clk,
        sdaIn,
        sdaOut,
        isSending,
        i2cScl,
        i2cInstruction,
        i2cEnable,
        i2cByteToSend,
        i2cByteReceived,
        i2cComplete
    );

    reg [1:0] adcChannel = 0;
    wire [15:0] adcOutputData;
    wire adcDataReady;
    reg adcEnable = 1;

    adc #(7'b1001001) a(
        clk,
        adcChannel,
        adcOutputData,
        adcDataReady,
        adcEnable,
        i2cInstruction,
        i2cEnable,
        i2cByteToSend,
        i2cByteReceived,
        i2cComplete
    );
endmodule

examples/adc/adc.vcd
$date
	Mon Dec 15 12:11:40 2025
$end
$version
	Icarus Verilog
$end
$timescale
	1s
$end
$scope module test $end
$var wire 1 ! sdaOut $end
$var wire 1 " sdaIn $end
$var wire 1 # isSending $end
$var wire 1 $ i2cSda $end
$var wire 1 % i2cScl $end
$var wire 2 & i2cInstruction [1:0] $end
$var wire 1 ' i2cEnable $end
$var wire 1 ( i2cComplete $end
$var wire 8 ) i2cByteToSend [7:0] $end
$var wire 8 * i2cByteReceived [7:0] $end
$var wire 16 + adcOutputData [15:0] $end
$var wire 1 , adcDataReady $end
$var reg 2 - adcChannel [1:0] $end
$var reg 1 . adcEnable $end
$var reg 1 / clk $end
$scope module a $end
$var wire 2 0 channel [1:0] $end
$var wire 1 / clk $end
$var wire 1 . enable $end
$var wire 1 ( completeI2C $end
$var wire 8 1 byteReceivedI2C [7:0] $end
$var parameter 8 2 CONFIG_REGISTER $end
$var parameter 8 3 CONVERSION_REGISTER $end
$var parameter 32 4 INST_READ_BYTE $end
$var parameter 32 5 INST_START_TX $end
$var parameter 32 6 INST_STOP_TX $end
$var parameter 32 7 INST_WRITE_BYTE $end
$var parameter 32 8 STATE_DELAY $end
$var parameter 32 9 STATE_DONE $end
$var parameter 32 : STATE_IDLE $end
$var parameter 32 ; STATE_INC_SUB_TASK $end
$var parameter 32 < STATE_RUN_TASK $end
$var parameter 32 = STATE_WAIT_FOR_I2C $end
$var parameter 32 > TASK_CHANGE_REG $end
$var parameter 32 ? TASK_CHECK_DONE $end
$var parameter 32 @ TASK_READ_VALUE $end
$var parameter 32 A TASK_SETUP $end
$var parameter 7 B address $end
$var reg 8 C byteToSendI2C [7:0] $end
$var reg 8 D counter [7:0] $end
$var reg 1 , dataReady $end
$var reg 1 ' enableI2C $end
$var reg 2 E instructionI2C [1:0] $end
$var reg 16 F outputData [15:0] $end
$var reg 1 G processStarted $end
$var reg 16 H setupRegister [15:0] $end
$var reg 5 I state [4:0] $end
$var reg 3 J subTaskIndex [2:0] $end
$var reg 2 K taskIndex [1:0] $end
$upscope $end
$scope module c $end
$var wire 8 L byteToSend [7:0] $end
$var wire 1 / clk $end
$var wire 1 ' enable $end
$var wire 2 M instruction [1:0] $end
$var wire 1 " sdaIn $end
$var parameter 32 N INST_READ_BYTE $end
$var parameter 32 O INST_START_TX $end
$var parameter 32 P INST_STOP_TX $end
$var parameter 32 Q INST_WRITE_BYTE $end
$var parameter 32 R STATE_DONE $end
$var parameter 32 S STATE_IDLE $end
$var parameter 32 T STATE_RCV_ACK $end
$var parameter 32 U STATE_SEND_ACK $end
$var reg 3 V bitToSend [2:0] $end
$var reg 8 W byteReceived [7:0] $end
$var reg 7 X clockDivider [6:0] $end
$var reg 1 ( complete $end
$var reg 1 # isSending $end
$var reg 1 % scl $end
$var reg 1 ! sdaOutReg $end
$var reg 3 Y state [2:0] $end
$upscope $end
$upscope $end
$enddefinitions $end
$comment Show the parameter values. $end
$dumpall
b110 U
b111 T
b100 S
b101 R
b11 Q
b1 P
b0 O
b10 N
b1001001 B
b0 A
b11 @
b1 ?
b10 >
b10 =
b1 <
b11 ;
b0 :
b100 9
b101 8
b11 7
b1 6
b0 5
b10 4
b0 3
b1 2
$end
#0
$dumpvars
b100 Y
b0 X
b0 W
b0 V
b0 M
b0 L
b0 K
b0 J
b0 I
b1100001110000011 H
0G
b0 F
b0 E
b0 D
b0 C
b0 1
b0 0
0/
1.
b0 -
1,
b0 +
b0 *
b0 )
x(
0'
b0 &
1%
1$
0#
1"
1!
$end
#1
0,
b1 I
1/
#2
0/
#3
b10 I
1'
1/
#4
0/
#5
b0 Y
0(
1/
#6
0/
#7
1G
b1 X
1#
1/
#8
0/
#9
b10 X
1/
#10
0/
#11
b11 X
1/
#12
0/
#13
b100 X
1/
#14
0/
#15
b101 X
1/
#16
0/
#17
b110 X
1/
#18
0/
#19
b111 X
1/
#20
0/
#21
b1000 X
1/
#22
0/
#23
b1001 X
1/
#24
0/
#25
b1010 X
1/
#26
0/
#27
b1011 X
1/
#28
0/
#29
b1100 X
1/
#30
0/
#31
b1101 X
1/
#32
0/
#33
b1110 X
1/
#34
0/
#35
b1111 X
1/
#36
0/
#37
b10000 X
1/
#38
0/
#39
b10001 X
1/
#40
0/
#41
b10010 X
1/
#42
0/
#43
b10011 X
1/
#44
0/
#45
b10100 X
1/
#46
0/
#47
b10101 X
1/
#48
0/
#49
b10110 X
1/
#50
0/
#51
b10111 X
1/
#52
0/
#53
b11000 X
1/
#54
0/
#55
b11001 X
1/
#56
0/
#57
b11010 X
1/
#58
0/
#59
b11011 X
1/
#60
0/
#61
b11100 X
1/
#62
0/
#63
b11101 X
1/
#64
0/
#65
b11110 X
1/
#66
0/
#67
b11111 X
1/
#68
0/
#69
b100000 X
1/
#70
0/
#71
0"
0$
0!
b100001 X
1/
#72
0/
#73
b100010 X
1/
#74
0/
#75
b100011 X
1/
#76
0/
#77
b100100 X
1/
#78
0/
#79
b100101 X
1/
#80
0/
#81
b100110 X
1/
#82
0/
#83
b100111 X
1/
#84
0/
#85
b101000 X
1/
#86
0/
#87
b101001 X
1/
#88
0/
#89
b101010 X
1/
#90
0/
#91
b101011 X
1/
#92
0/
#93
b101100 X
1/
#94
0/
#95
b101101 X
1/
#96
0/
#97
b101110 X
1/
#98
0/
#99
b101111 X
1/
#100
0/
#101
b110000 X
1/
#102
0/
#103
b110001 X
1/
#104
0/
#105
b110010 X
1/
#106
0/
#107
b110011 X
1/
#108
0/
#109
b110100 X
1/
#110
0/
#111
b110101 X
1/
#112
0/
#113
b110110 X
1/
#114
0/
#115
b110111 X
1/
#116
0/
#117
b111000 X
1/
#118
0/
#119
b111001 X
1/
#120
0/
#121
b111010 X
1/
#122
0/
#123
b111011 X
1/
#124
0/
#125
b111100 X
1/
#126
0/
#127
b111101 X
1/
#128
0/
#129
b111110 X
1/
#130
0/
#131
b111111 X
1/
#132
0/
#133
b1000000 X
1/
#134
0/
#135
0%
b1000001 X
1/
#136
0/
#137
b1000010 X
1/
#138
0/
#139
b1000011 X
1/
#140
0/
#141
b1000100 X
1/
#142
0/
#143
b1000101 X
1/
#144
0/
#145
b1000110 X
1/
#146
0/
#147
b1000111 X
1/
#148
0/
#149
b1001000 X
1/
#150
0/
#151
b1001001 X
1/
#152
0/
#153
b1001010 X
1/
#154
0/
#155
b1001011 X
1/
#156
0/
#157
b1001100 X
1/
#158
0/
#159
b1001101 X
1/
#160
0/
#161
b1001110 X
1/
#162
0/
#163
b1001111 X
1/
#164
0/
#165
b1010000 X
1/
#166
0/
#167
b1010001 X
1/
#168
0/
#169
b1010010 X
1/
#170
0/
#171
b1010011 X
1/
#172
0/
#173
b1010100 X
1/
#174
0/
#175
b1010101 X
1/
#176
0/
#177
b1010110 X
1/
#178
0/
#179
b1010111 X
1/
#180
0/
#181
b1011000 X
1/
#182
0/
#183
b1011001 X
1/
#184
0/
#185
b1011010 X
1/
#186
0/
#187
b1011011 X
1/
#188
0/
#189
b1011100 X
1/
#190
0/
#191
b1011101 X
1/
#192
0/
#193
b1011110 X
1/
#194
0/
#195
b1011111 X
1/
#196
0/
#197
b1100000 X
1/
#198
0/
#199
b101 Y
b1100001 X
1/
#200
0/
#201
1(
1/
#202
0/
#203
0'
0G
b11 I
1/
#204
0/
#205
b100 Y
b1 J
b1 I
1/
#206
0/
#207
b10 I
1'
b10010010 )
b10010010 C
b10010010 L
b11 &
b11 E
b11 M
1/
#208
0/
#209
b11 Y
b0 X
0(
1/
#210
0/
#211
1"
1$
1G
1!
b1 X
1/
#212
0/
#213
b10 X
1/
#214
0/
#215
b11 X
1/
#216
0/
#217
b100 X
1/
#218
0/
#219
b101 X
1/
#220
0/
#221
b110 X
1/
#222
0/
#223
b111 X
1/
#224
0/
#225
b1000 X
1/
#226
0/
#227
b1001 X
1/
#228
0/
#229
b1010 X
1/
#230
0/
#231
b1011 X
1/
#232
0/
#233
b1100 X
1/
#234
0/
#235
b1101 X
1/
#236
0/
#237
b1110 X
1/
#238
0/
#239
b1111 X
1/
#240
0/
#241
b10000 X
1/
#242
0/
#243
b10001 X
1/
#244
0/
#245
b10010 X
1/
#246
0/
#247
b10011 X
1/
#248
0/
#249
b10100 X
1/
#250
0/
#251
b10101 X
1/
#252
0/
#253
b10110 X
1/
#254
0/
#255
b10111 X
1/
#256
0/
#257
b11000 X
1/
#258
0/
#259
b11001 X
1/
#260
0/
#261
b11010 X
1/
#262
0/
#263
b11011 X
1/
#264
0/
#265
b11100 X
1/
#266
0/
#267
b11101 X
1/
#268
0/
#269
b11110 X
1/
#270
0/
#271
b11111 X
1/
#272
0/
#273
b100000 X
1/
#274
0/
#275
1%
b100001 X
1/
#276
0/
#277
b100010 X
1/
#278
0/
#279
b100011 X
1/
#280
0/
#281
b100100 X
1/
#282
0/
#283
b100101 X
1/
#284
0/
#285
b100110 X
1/
#286
0/
#287
b100111 X
1/
#288
0/
#289
b101000 X
1/
#290
0/
#291
b101001 X
1/
#292
0/
#293
b101010 X
1/
#294
0/
#295
b101011 X
1/
#296
0/
#297
b101100 X
1/
#298
0/
#299
b101101 X
1/
#300
0/
#301
b101110 X
1/
#302
0/
#303
b101111 X
1/
#304
0/
#305
b110000 X
1/
#306
0/
#307
b110001 X
1/
#308
0/
#309
b110010 X
1/
#310
0/
#311
b110011 X
1/
#312
0/
#313
b110100 X
1/
#314
0/
#315
b110101 X
1/
#316
0/
#317
b110110 X
1/
#318
0/
#319
b110111 X
1/
#320
0/
#321
b111000 X
1/
#322
0/
#323
b111001 X
1/
#324
0/
#325
b111010 X
1/
#326
0/
#327
b111011 X
1/
#328
0/
#329
b111100 X
1/
#330
0/
#331
b111101 X
1/
#332
0/
#333
b111110 X
1/
#334
0/
#335
b111111 X
1/
#336
0/
#337
b1000000 X
1/
#338
0/
#339
b1000001 X
1/
#340
0/
#341
b1000010 X
1/
#342
0/
#343
b1000011 X
1/
#344
0/
#345
b1000100 X
1/
#346
0/
#347
b1000101 X
1/
#348
0/
#349
b1000110 X
1/
#350
0/
#351
b1000111 X
1/
#352
0/
#353
b1001000 X
1/
#354
0/
#355
b1001001 X
1/
#356
0/
#357
b1001010 X
1/
#358
0/
#359
b1001011 X
1/
#360
0/
#361
b1001100 X
1/
#362
0/
#363
b1001101 X
1/
#364
0/
#365
b1001110 X
1/
#366
0/
#367
b1001111 X
1/
#368
0/
#369
b1010000 X
1/
#370
0/
#371
b1010001 X
1/
#372
0/
#373
b1010010 X
1/
#374
0/
#375
b1010011 X
1/
#376
0/
#377
b1010100 X
1/
#378
0/
#379
b1010101 X
1/
#380
0/
#381
b1010110 X
1/
#382
0/
#383
b1010111 X
1/
#384
0/
#385
b1011000 X
1/
#386
0/
#387
b1011001 X
1/
#388
0/
#389
b1011010 X
1/
#390
0/
#391
b1011011 X
1/
#392
0/
#393
b1011100 X
1/
#394
0/
#395
b1011101 X
1/
#396
0/
#397
b1011110 X
1/
#398
0/
#399
b1011111 X
1/
#400
0/
#401
b1100000 X
1/
#402
0/
#403
0%
b1100001 X
1/
#404
0/
#405
b1100010 X
1/
#406
0/
#407
b1100011 X
1/
#408
0/
#409
b1100100 X
1/
#410
0/
#411
b1100101 X
1/
#412
0/
#413
b1100110 X
1/
#414
0/
#415
b1100111 X
1/
#416
0/
#417
b1101000 X
1/
#418
0/
#419
b1101001 X
1/
#420
0/
#421
b1101010 X
1/
#422
0/
#423
b1101011 X
1/
#424
0/
#425
b1101100 X
1/
#426
0/
#427
b1101101 X
1/
#428
0/
#429
b1101110 X
1/
#430
0/
#431
b1101111 X
1/
#432
0/
#433
b1110000 X
1/
#434
0/
#435
b1110001 X
1/
#436
0/
#437
b1110010 X
1/
#438
0/
#439
b1110011 X
1/
#440
0/
#441
b1110100 X
1/
#442
0/
#443
b1110101 X
1/
#444
0/
#445
b1110110 X
1/
#446
0/
#447
b1110111 X
1/
#448
0/
#449
b1111000 X
1/
#450
0/
#451
b1111001 X
1/
#452
0/
#453
b1111010 X
1/
#454
0/
#455
b1111011 X
1/
#456
0/
#457
b1111100 X
1/
#458
0/
#459
b1111101 X
1/
#460
0/
#461
b1111110 X
1/
#462
0/
#463
b1111111 X
1/
#464
0/
#465
b1 V
b0 X
1/
#466
0/
#467
0"
0$
0!
b1 X
1/
#468
0/
#469
b10 X
1/
#470
0/
#471
b11 X
1/
#472
0/
#473
b100 X
1/
#474
0/
#475
b101 X
1/
#476
0/
#477
b110 X
1/
#478
0/
#479
b111 X
1/
#480
0/
#481
b1000 X
1/
#482
0/
#483
b1001 X
1/
#484
0/
#485
b1010 X
1/
#486
0/
#487
b1011 X
1/
#488
0/
#489
b1100 X
1/
#490
0/
#491
b1101 X
1/
#492
0/
#493
b1110 X
1/
#494
0/
#495
b1111 X
1/
#496
0/
#497
b10000 X
1/
#498
0/
#499
b10001 X
1/
#500
0/
#501
b10010 X
1/
#502
0/
#503
b10011 X
1/
#504
0/
#505
b10100 X
1/
#506
0/
#507
b10101 X
1/
#508
0/
#509
b10110 X
1/
#510
0/
#511
b10111 X
1/
#512
0/
#513
b11000 X
1/
#514
0/
#515
b11001 X
1/
#516
0/
#517
b11010 X
1/
#518
0/
#519
b11011 X
1/
#520
0/
#521
b11100 X
1/
#522
0/
#523
b11101 X
1/
#524
0/
#525
b11110 X
1/
#526
0/
#527
b11111 X
1/
#528
0/
#529
b100000 X
1/
#530
0/
#531
1%
b100001 X
1/
#532
0/
#533
b100010 X
1/
#534
0/
#535
b100011 X
1/
#536
0/
#537
b100100 X
1/
#538
0/
#539
b100101 X
1/
#540
0/
#541
b100110 X
1/
#542
0/
#543
b100111 X
1/
#544
0/
#545
b101000 X
1/
#546
0/
#547
b101001 X
1/
#548
0/
#549
b101010 X
1/
#550
0/
#551
b101011 X
1/
#552
0/
#553
b101100 X
1/
#554
0/
#555
b101101 X
1/
#556
0/
#557
b101110 X
1/
#558
0/
#559
b101111 X
1/
#560
0/
#561
b110000 X
1/
#562
0/
#563
b110001 X
1/
#564
0/
#565
b110010 X
1/
#566
0/
#567
b110011 X
1/
#568
0/
#569
b110100 X
1/
#570
0/
#571
b110101 X
1/
#572
0/
#573
b110110 X
1/
#574
0/
#575
b110111 X
1/
#576
0/
#577
b111000 X
1/
#578
0/
#579
b111001 X
1/
#580
0/
#581
b111010 X
1/
#582
0/
#583
b111011 X
1/
#584
0/
#585
b111100 X
1/
#586
0/
#587
b111101 X
1/
#588
0/
#589
b111110 X
1/
#590
0/
#591
b111111 X
1/
#592
0/
#593
b1000000 X
1/
#594
0/
#595
b1000001 X
1/
#596
0/
#597
b1000010 X
1/
#598
0/
#599
b1000011 X
1/
#600
0/
#601
b1000100 X
1/
#602
0/
#603
b1000101 X
1/
#604
0/
#605
b1000110 X
1/
#606
0/
#607
b1000111 X
1/
#608
0/
#609
b1001000 X
1/
#610
0/
#611
b1001001 X
1/
#612
0/
#613
b1001010 X
1/
#614
0/
#615
b1001011 X
1/
#616
0/
#617
b1001100 X
1/
#618
0/
#619
b1001101 X
1/
#620
0/
#621
b1001110 X
1/
#622
0/
#623
b1001111 X
1/
#624
0/
#625
b1010000 X
1/
#626
0/
#627
b1010001 X
1/
#628
0/
#629
b1010010 X
1/
#630
0/
#631
b1010011 X
1/
#632
0/
#633
b1010100 X
1/
#634
0/
#635
b1010101 X
1/
#636
0/
#637
b1010110 X
1/
#638
0/
#639
b1010111 X
1/
#640
0/
#641
b1011000 X
1/
#642
0/
#643
b1011001 X
1/
#644
0/
#645
b1011010 X
1/
#646
0/
#647
b1011011 X
1/
#648
0/
#649
b1011100 X
1/
#650
0/
#651
b1011101 X
1/
#652
0/
#653
b1011110 X
1/
#654
0/
#655
b1011111 X
1/
#656
0/
#657
b1100000 X
1/
#658
0/
#659
0%
b1100001 X
1/
#660
0/
#661
b1100010 X
1/
#662
0/
#663
b1100011 X
1/
#664
0/
#665
b1100100 X
1/
#666
0/
#667
b1100101 X
1/
#668
0/
#669
b1100110 X
1/
#670
0/
#671
b1100111 X
1/
#672
0/
#673
b1101000 X
1/
#674
0/
#675
b1101001 X
1/
#676
0/
#677
b1101010 X
1/
#678
0/
#679
b1101011 X
1/
#680
0/
#681
b1101100 X
1/
#682
0/
#683
b1101101 X
1/
#684
0/
#685
b1101110 X
1/
#686
0/
#687
b1101111 X
1/
#688
0/
#689
b1110000 X
1/
#690
0/
#691
b1110001 X
1/
#692
0/
#693
b1110010 X
1/
#694
0/
#695
b1110011 X
1/
#696
0/
#697
b1110100 X
1/
#698
0/
#699
b1110101 X
1/
#700
0/
#701
b1110110 X
1/
#702
0/
#703
b1110111 X
1/
#704
0/
#705
b1111000 X
1/
#706
0/
#707
b1111001 X
1/
#708
0/
#709
b1111010 X
1/
#710
0/
#711
b1111011 X
1/
#712
0/
#713
b1111100 X
1/
#714
0/
#715
b1111101 X
1/
#716
0/
#717
b1111110 X
1/
#718
0/
#719
b1111111 X
1/
#720
0/
#721
b10 V
b0 X
1/
#722
0/
#723
b1 X
1/
#724
0/
#725
b10 X
1/
#726
0/
#727
b11 X
1/
#728
0/
#729
b100 X
1/
#730
0/
#731
b101 X
1/
#732
0/
#733
b110 X
1/
#734
0/
#735
b111 X
1/
#736
0/
#737
b1000 X
1/
#738
0/
#739
b1001 X
1/
#740
0/
#741
b1010 X
1/
#742
0/
#743
b1011 X
1/
#744
0/
#745
b1100 X
1/
#746
0/
#747
b1101 X
1/
#748
0/
#749
b1110 X
1/
#750
0/
#751
b1111 X
1/
#752
0/
#753
b10000 X
1/
#754
0/
#755
b10001 X
1/
#756
0/
#757
b10010 X
1/
#758
0/
#759
b10011 X
1/
#760
0/
#761
b10100 X
1/
#762
0/
#763
b10101 X
1/
#764
0/
#765
b10110 X
1/
#766
0/
#767
b10111 X
1/
#768
0/
#769
b11000 X
1/
#770
0/
#771
b11001 X
1/
#772
0/
#773
b11010 X
1/
#774
0/
#775
b11011 X
1/
#776
0/
#777
b11100 X
1/
#778
0/
#779
b11101 X
1/
#780
0/
#781
b11110 X
1/
#782
0/
#783
b11111 X
1/
#784
0/
#785
b100000 X
1/
#786
0/
#787
1%
b100001 X
1/
#788
0/
#789
b100010 X
1/
#790
0/
#791
b100011 X
1/
#792
0/
#793
b100100 X
1/
#794
0/
#795
b100101 X
1/
#796
0/
#797
b100110 X
1/
#798
0/
#799
b100111 X
1/
#800
0/
#801
b101000 X
1/
#802
0/
#803
b101001 X
1/
#804
0/
#805
b101010 X
1/
#806
0/
#807
b101011 X
1/
#808
0/
#809
b101100 X
1/
#810
0/
#811
b101101 X
1/
#812
0/
#813
b101110 X
1/
#814
0/
#815
b101111 X
1/
#816
0/
#817
b110000 X
1/
#818
0/
#819
b110001 X
1/
#820
0/
#821
b110010 X
1/
#822
0/
#823
b110011 X
1/
#824
0/
#825
b110100 X
1/
#826
0/
#827
b110101 X
1/
#828
0/
#829
b110110 X
1/
#830
0/
#831
b110111 X
1/
#832
0/
#833
b111000 X
1/
#834
0/
#835
b111001 X
1/
#836
0/
#837
b111010 X
1/
#838
0/
#839
b111011 X
1/
#840
0/
#841
b111100 X
1/
#842
0/
#843
b111101 X
1/
#844
0/
#845
b111110 X
1/
#846
0/
#847
b111111 X
1/
